{
  "platforms": [ "apple", "android", "devtools" ],
  "apple": {
    "appDelegateSubscribers": [ "BackgroundTaskAppDelegateSubscriber" ],
    "modules": [ "BackgroundTaskModule" ]
  },
  "android": {
    "modules": [ "expo.modules.backgroundtask.BackgroundTaskModule" ]
  },
  "devtools": {
    "cli": {
      "description": "Expo: manage background tasks",
      "commands": [
        { "name": "list", "caption": "List registered background tasks" },
        { "name": "test", "caption": "Trigger background tasks" }
      ],
      "main": "cliext/build/index.js"
    }
  }
}
