{"name":"expo-keep-awake","kind":1,"kindString":"Project","originalName":"","children":[{"name":"ExpoKeepAwakeTag","kind":32,"kindString":"Variable","flags":{"isConst":true},"type":{"type":"literal","value":"ExpoKeepAwakeDefaultTag"},"defaultValue":"'ExpoKeepAwakeDefaultTag'"},{"name":"activateKeepAwake","kind":64,"kindString":"Function","signatures":[{"name":"activateKeepAwake","kind":4096,"kindString":"Call signature","comment":{"summary":[{"kind":"text","text":"Prevents the screen from sleeping until "},{"kind":"code","text":"`deactivateKeepAwake`"},{"kind":"text","text":" is called with the same "},{"kind":"code","text":"`tag`"},{"kind":"text","text":" value.\n\nIf the "},{"kind":"code","text":"`tag`"},{"kind":"text","text":" argument is specified, the screen will not sleep until you call "},{"kind":"code","text":"`deactivateKeepAwake`"},{"kind":"text","text":"\nwith the same "},{"kind":"code","text":"`tag`"},{"kind":"text","text":" argument. When using multiple "},{"kind":"code","text":"`tags`"},{"kind":"text","text":" for activation you'll have to deactivate\neach one in order to re-enable screen sleep. If tag is unspecified, the default "},{"kind":"code","text":"`tag`"},{"kind":"text","text":" is used."}]},"parameters":[{"name":"tag","kind":32768,"kindString":"Parameter","comment":{"summary":[{"kind":"text","text":"*Optional* - Tag to lock screen sleep prevention. If not provided, the default tag is used."}]},"type":{"type":"intrinsic","name":"string"},"defaultValue":"ExpoKeepAwakeTag"}],"type":{"type":"reference","typeArguments":[{"type":"intrinsic","name":"void"}],"name":"Promise","qualifiedName":"Promise","package":"typescript"}}]},{"name":"deactivateKeepAwake","kind":64,"kindString":"Function","signatures":[{"name":"deactivateKeepAwake","kind":4096,"kindString":"Call signature","comment":{"summary":[{"kind":"text","text":"Releases the lock on screen-sleep prevention associated with the given "},{"kind":"code","text":"`tag`"},{"kind":"text","text":" value. If "},{"kind":"code","text":"`tag`"},{"kind":"text","text":"\nis unspecified, it defaults to the same default tag that "},{"kind":"code","text":"`activateKeepAwake`"},{"kind":"text","text":" uses."}]},"parameters":[{"name":"tag","kind":32768,"kindString":"Parameter","comment":{"summary":[{"kind":"text","text":"*Optional* - Tag to release the lock on screen sleep prevention. If not provided,\nthe default tag is used."}]},"type":{"type":"intrinsic","name":"string"},"defaultValue":"ExpoKeepAwakeTag"}],"type":{"type":"reference","typeArguments":[{"type":"intrinsic","name":"void"}],"name":"Promise","qualifiedName":"Promise","package":"typescript"}}]},{"name":"useKeepAwake","kind":64,"kindString":"Function","signatures":[{"name":"useKeepAwake","kind":4096,"kindString":"Call signature","comment":{"summary":[{"kind":"text","text":"A React hook to keep the screen awake for as long as the owner component is mounted.\nThe optionally provided "},{"kind":"code","text":"`tag`"},{"kind":"text","text":" argument is used when activating and deactivating the keep-awake\nfeature. If unspecified, the default "},{"kind":"code","text":"`tag`"},{"kind":"text","text":" is used. See the documentation for "},{"kind":"code","text":"`activateKeepAwake`"},{"kind":"text","text":"\nbelow to learn more about the "},{"kind":"code","text":"`tag`"},{"kind":"text","text":" argument."}]},"parameters":[{"name":"tag","kind":32768,"kindString":"Parameter","comment":{"summary":[{"kind":"text","text":"*Optional* - Tag to lock screen sleep prevention. If not provided, the default tag is used."}]},"type":{"type":"intrinsic","name":"string"},"defaultValue":"ExpoKeepAwakeTag"},{"name":"options","kind":32768,"kindString":"Parameter","flags":{"isOptional":true},"comment":{"summary":[{"kind":"text","text":"*Optional*\n  - "},{"kind":"code","text":"`suppressDeactivateWarnings`"},{"kind":"text","text":" *Optional* -\n     The call will throw an unhandled promise rejection on Android\n     when the original Activity is dead or deactivated.\n     Set the value to true for suppressing the uncaught exception."}]},"type":{"type":"reflection","declaration":{"name":"__type","kind":65536,"kindString":"Type literal","children":[{"name":"suppressDeactivateWarnings","kind":1024,"kindString":"Property","type":{"type":"intrinsic","name":"boolean"}}]}}}],"type":{"type":"intrinsic","name":"void"}}]}]}